LICENSE.txt
MANIFEST.in
README.rst
setup.py
lars/__init__.py
lars/apache.py
lars/cache.py
lars/csv.py
lars/dns.py
lars/exc.py
lars/geoip.py
lars/iis.py
lars/parsers.py
lars/progress.py
lars/sql.py
lars/strptime.py
lars/timezone.py
lars.egg-info/PKG-INFO
lars.egg-info/SOURCES.txt
lars.egg-info/dependency_links.txt
lars.egg-info/requires.txt
lars.egg-info/top_level.txt
lars/datatypes/__init__.py
lars/datatypes/datetime.py
lars/datatypes/ipaddress.py
lars/datatypes/url.py
tests/__init__.py
tests/test_apache.py
tests/test_cache.py
tests/test_csv.py
tests/test_datatypes.py
tests/test_dns.py
tests/test_geoip.py
tests/test_iis.py
tests/test_parsers.py
tests/test_progress.py
tests/test_sql.py