Metadata-Version: 1.1
Name: lars
Version: 1.0
Summary: A framework for converting web-logs into various formats
Home-page: http://github.com/waveform80/lars
Author: Dave Jones
Author-email: dave@waveform.org.uk
License: MIT License
Keywords: web,www,logs,database
Platform: ALL
Classifier: Development Status :: 5 - Production/Stable
Classifier: Intended Audience :: System Administrators
Classifier: License :: OSI Approved :: MIT License
Classifier: Operating System :: Microsoft :: Windows
Classifier: Operating System :: POSIX
Classifier: Operating System :: Unix
Classifier: Programming Language :: Python :: 2.7
Classifier: Programming Language :: Python :: 3
Classifier: Topic :: Internet :: WWW/HTTP :: Site Management
Classifier: Topic :: Text Processing
